plone.dexterity-3.0.8-py3.13-nspkg.pth
plone/dexterity/__init__.py
plone/dexterity/behavior.py
plone/dexterity/configure.zcml
plone/dexterity/content.py
plone/dexterity/events.py
plone/dexterity/exportimport.py
plone/dexterity/factory.py
plone/dexterity/filerepresentation.py
plone/dexterity/fti.py
plone/dexterity/i18n.py
plone/dexterity/interfaces.py
plone/dexterity/meta.zcml
plone/dexterity/primary.py
plone/dexterity/schema.py
plone/dexterity/synchronize.py
plone/dexterity/utils.py
plone/dexterity/browser/__init__.py
plone/dexterity/browser/add.py
plone/dexterity/browser/base.py
plone/dexterity/browser/configure.zcml
plone/dexterity/browser/containercontentcore.pt
plone/dexterity/browser/edit.py
plone/dexterity/browser/fti.pt
plone/dexterity/browser/fti.py
plone/dexterity/browser/item.pt
plone/dexterity/browser/itemcontentcore.pt
plone/dexterity/browser/traversal.py
plone/dexterity/browser/view.py
plone/dexterity/browser/icons/container_icon.gif
plone/dexterity/browser/icons/item_icon.gif
plone/dexterity/browser/icons/typeinfo.gif
plone/dexterity/tests/__init__.py
plone/dexterity/tests/case.py
plone/dexterity/tests/schemata.py
plone/dexterity/tests/test.xml
plone/dexterity/tests/test_behavior.py
plone/dexterity/tests/test_content.py
plone/dexterity/tests/test_content_integration.py
plone/dexterity/tests/test_exportimport.py
plone/dexterity/tests/test_factory.py
plone/dexterity/tests/test_filerepresentation.py
plone/dexterity/tests/test_fti.py
plone/dexterity/tests/test_primary.py
plone/dexterity/tests/test_schema.py
plone/dexterity/tests/test_schema_cache.py
plone/dexterity/tests/test_security.py
plone/dexterity/tests/test_synchronize.py
plone/dexterity/tests/test_utils.py
plone/dexterity/tests/test_views.py
plone/dexterity/tests/test_webdav.py
plone_dexterity-3.0.8.dist-info/METADATA
plone_dexterity-3.0.8.dist-info/WHEEL
plone_dexterity-3.0.8.dist-info/namespace_packages.txt
plone_dexterity-3.0.8.dist-info/top_level.txt
plone_dexterity-3.0.8.dist-info/RECORD
