Metadata-Version: 2.4
Name: plone.dexterity
Version: 3.0.8
Summary: Framework for content types as filesystem code and TTW (Zope/CMF/Plone)
Home-page: https://github.com/plone/plone.dexterity
Author: Martin Aspeli
Author-email: optilude@gmail.com
Maintainer: The Plone Release Team and Community
Maintainer-email: releaseteam@plone.org
License: GPL version 2
Keywords: plone dexterity contenttypes
Classifier: Development Status :: 5 - Production/Stable
Classifier: Framework :: Plone
Classifier: Framework :: Plone :: 6.0
Classifier: Framework :: Plone :: Core
Classifier: License :: OSI Approved :: GNU General Public License v2 (GPLv2)
Classifier: Programming Language :: Python
Classifier: Programming Language :: Python :: 3.8
Classifier: Programming Language :: Python :: 3.9
Classifier: Programming Language :: Python :: 3.10
Classifier: Programming Language :: Python :: 3.11
Classifier: Topic :: Software Development :: Libraries :: Python Modules
Requires-Python: >=3.8
Requires-Dist: Products.CMFCore
Requires-Dist: Products.statusmessages
Requires-Dist: Zope
Requires-Dist: plone.alterego
Requires-Dist: plone.app.uuid
Requires-Dist: plone.autoform>=1.0
Requires-Dist: plone.base
Requires-Dist: plone.behavior>=1.0
Requires-Dist: plone.folder
Requires-Dist: plone.memoize
Requires-Dist: plone.rfc822
Requires-Dist: plone.supermodel>=1.0
Requires-Dist: plone.uuid
Requires-Dist: z3c.form
Requires-Dist: setuptools
Provides-Extra: test
Requires-Dist: plone.testing; extra == "test"
Requires-Dist: plone.app.content; extra == "test"
Requires-Dist: plone.i18n; extra == "test"
Dynamic: author
Dynamic: author-email
Dynamic: classifier
Dynamic: description
Dynamic: description-content-type
Dynamic: home-page
Dynamic: keywords
Dynamic: license
Dynamic: maintainer
Dynamic: maintainer-email
Dynamic: provides-extra
Dynamic: requires-dist
Dynamic: requires-python
Dynamic: summary
